p1255/__init__.py
p1255/__main__.py
p1255/commands.py
p1255/constants.py
p1255/data.py
p1255/gui.py
p1255/gui.ui
p1255/p1255.py
p1255-0.3.4.dist-info/licenses/LICENSE
p1255-0.3.4.dist-info/METADATA
p1255-0.3.4.dist-info/WHEEL
p1255-0.3.4.dist-info/entry_points.txt
p1255-0.3.4.dist-info/top_level.txt
p1255-0.3.4.dist-info/RECORD
