Metadata-Version: 2.4
Name: p1255
Version: 0.3.4
Summary: PeakTech P1255 Oscilloscope Tool
Author-email: Michael Hohenstein <michael@hohenste.in>
License-Expression: GPL-3.0-or-later
Project-URL: Homepage, https://github.com/MitchiLaser/p1255
Project-URL: Repository, https://github.com/MitchiLaser/p1255
Keywords: Oscilloscope
Classifier: Development Status :: 5 - Production/Stable
Classifier: Intended Audience :: Education
Classifier: Intended Audience :: Science/Research
Classifier: Topic :: Education
Classifier: Topic :: Scientific/Engineering
Classifier: Topic :: Scientific/Engineering :: Physics
Classifier: Programming Language :: Python :: 3
Classifier: Programming Language :: Python :: 3.10
Classifier: Programming Language :: Python :: 3.11
Classifier: Programming Language :: Python :: 3.12
Classifier: Programming Language :: Python :: 3.13
Requires-Python: >=3.10
License-File: LICENSE
Requires-Dist: PyQt5
Requires-Dist: matplotlib
Requires-Dist: numpy
Requires-Dist: pyyaml
Requires-Dist: pandas
Requires-Dist: hexdump
Requires-Dist: tqdm
Dynamic: license-file
